pg_configuration/__init__.py
pg_configuration/configuration.py
pg_configuration/define.py
pg_configuration-1.1.2.dist-info/METADATA
pg_configuration-1.1.2.dist-info/WHEEL
pg_configuration-1.1.2.dist-info/top_level.txt
pg_configuration-1.1.2.dist-info/RECORD
