Metadata-Version: 2.1
Name: pg_configuration
Version: 1.1.2
Summary: python game: configuration
Author: baozilaji@gmail.com
Requires-Python: >=3.9
Requires-Dist: pg-environment >=0
Requires-Dist: openpyxl ==3.1.2
